<?xml version="1.0" encoding="utf-8" ?>
<Defs>
	<FactionColonies.FCEventDef>
		<defName>Null</defName> <!-- DefName -->
		<label>null</label> <!-- label for the event -->
		<timeTillTrigger>0</timeTillTrigger> <!-- Put a number in here to set an static time -->
		<desc>A blank event.</desc> <!-- Description of the event -->
		<location>0</location> <!-- the integer location of the event. Based on the int tile location -->
		<hasDestination>false</hasDestination> <!-- if the event has a set destination that can be called upon (settlements) -->
			

			
		<goods>  <!-- Put stuff in here if you want it to be given to the player after the event -->
		    <!-- <li> put thing here </li> -->
		</goods>
	</FactionColonies.FCEventDef>
	
	
	<FactionColonies.FCEventDef>
		<defName>settleNewColony</defName>
		<label>Settle Colony</label>
		<timeTillTrigger>0</timeTillTrigger> 
		<hasDestination>false</hasDestination>
		<desc>A caravan is forming a new colony.</desc> 
		<location>0</location> 
			

			
		<goods>  
		    <!-- <li> put thing here </li> -->
		</goods>
	</FactionColonies.FCEventDef>
	
	<FactionColonies.FCEventDef>
		<defName>taxColony</defName>
		<label>Settlment Taxes En-route</label>
		<timeTillTrigger>0</timeTillTrigger> 
		<hasDestination>false</hasDestination>
		<desc>A caravan is delivering taxes.</desc> 
		<location>0</location> 
			
		<goods>  
		    <!-- <li> put thing here </li> -->
		</goods>
	</FactionColonies.FCEventDef>



	
	<FactionColonies.FCEventDef>
		<defName>constructBuilding</defName>
		<label>Constructing Building</label>
		<timeTillTrigger>0</timeTillTrigger> 
		<hasDestination>false</hasDestination>
		<desc>A building is being constructed.</desc> 
		<location>0</location> 
		<goods>  
		    <!-- <li> put thing here </li> -->
		</goods>
	</FactionColonies.FCEventDef>
	
	
	<FactionColonies.FCEventDef>
		<defName>enactSettlementPolicy</defName>
		<label>Enacting a Policy</label>
		<timeTillTrigger>0</timeTillTrigger> 
		<hasDestination>false</hasDestination>
		<desc>A settlement-wide policy is being enacted.</desc> 
		<location>0</location> 
		<goods>  
		    <!-- <li> put thing here </li> -->
		</goods>
	</FactionColonies.FCEventDef>
	
	
	<FactionColonies.FCEventDef>
		<defName>enactFactionPolicy</defName>
		<label>Enacting a Policy</label>
		<timeTillTrigger>0</timeTillTrigger> 
		<hasDestination>false</hasDestination>
		<desc>A faction-wide policy is being enacted.</desc> 
		<location>0</location> 
		<goods>  
		    <!-- <li> put thing here </li> -->
		</goods>
	</FactionColonies.FCEventDef>
	
	<FactionColonies.FCEventDef>
		<defName>upgradeSettlement</defName>
		<label>Upgrading A Settlement</label>
		<timeTillTrigger>0</timeTillTrigger>
		<hasDestination>false</hasDestination>
		<desc>A settlement is being upgraded.</desc>
		<location>0</location>
		<goods>  
		    <!-- <li> put thing here </li> -->
		</goods>
	</FactionColonies.FCEventDef>
	
</Defs>